[
  {
    "_id": "M101",
    "name": "Introduction to Rocket Propulsion",
    "description": "Basic principles of rocket propulsion and rocket engines.",
    "course": "RS101",
    "lessons": [
      {
        "_id": "L101",
        "name": "Rocket Propulsion Basics",
        "description": "Overview of rocket propulsion fundamentals.",
        "module": "M101"
      },
      {
        "_id": "L102",
        "name": "Thrust and Propellant",
        "description": "Thrust generation and types of rocket propellants.",
        "module": "M101"
      },
      {
        "_id": "L103",
        "name": "Rocket Thrust Calculation",
        "description": "Calculating thrust generated by rocket engines.",
        "module": "M101"
      },
      {
        "_id": "L104",
        "name": "Rocket Propellant Types",
        "description": "In-depth analysis of various rocket propellant types.",
        "module": "M101"
      }
    ]
  },
  {
    "_id": "M102",
    "name": "Fuel and Combustion",
    "description": "Understanding rocket fuel, combustion processes, and efficiency.",
    "course": "RS101",
    "lessons": [
      {
        "_id": "L105",
        "name": "Types of Rocket Fuels",
        "description": "Overview of different types of rocket fuels.",
        "module": "M102"
      },
      {
        "_id": "L106",
        "name": "Combustion Efficiency",
        "description": "Measuring and optimizing combustion efficiency.",
        "module": "M102"
      },
      {
        "_id": "L107",
        "name": "Emissions Control",
        "description": "Controlling emissions during rocket combustion.",
        "module": "M102"
      }
    ]
  },
  {
    "_id": "M103",
    "name": "Nozzle Design",
    "description": "Principles of rocket nozzle design and performance optimization.",
    "course": "RS101",
    "lessons": [
      {
        "_id": "L108",
        "name": "Nozzle Shapes and Performance",
        "description": "Effect of nozzle shapes on rocket performance.",
        "module": "M103"
      },
      {
        "_id": "L109",
        "name": "Nozzle Materials",
        "description": "Material selection for rocket nozzles.",
        "module": "M103"
      },
      {
        "_id": "L110",
        "name": "Thrust Vector Control",
        "description": "Implementing thrust vector control systems in nozzle design.",
        "module": "M103"
      }
    ]
  },
  {
    "_id": "M201",
    "name": "Fundamentals of Aerodynamics",
    "description": "Basic aerodynamic concepts and fluid dynamics principles.",
    "course": "RS102",
    "lessons": [
      {
        "_id": "L201",
        "name": "Aerodynamic Principles",
        "description": "Fundamentals of aerodynamics and airfoil design.",
        "module": "M201"
      },
      {
        "_id": "L202",
        "name": "Aerodynamic Lift and Drag",
        "description": "Exploring lift and drag forces in aerodynamics.",
        "module": "M201"
      },
      {
        "_id": "L203",
        "name": "Airfoil Shapes",
        "description": "Designing airfoils for specific aerodynamic requirements.",
        "module": "M201"
      }
    ]
  },
  {
    "_id": "M202",
    "name": "Subsonic and Supersonic Flow",
    "description": "Understanding subsonic and supersonic aerodynamic behaviors.",
    "course": "RS102",
    "lessons": [
      {
        "_id": "L204",
        "name": "Subsonic Flow Theory",
        "description": "Exploration of subsonic airflow phenomena.",
        "module": "M202"
      },
      {
        "_id": "L205",
        "name": "Shock Waves",
        "description": "Understanding shock waves in supersonic flow.",
        "module": "M202"
      },
      {
        "_id": "L206",
        "name": "Hypersonic Flight",
        "description": "Exploration of hypersonic flight and its challenges.",
        "module": "M202"
      }
    ]
  },
  {
    "_id": "M203",
    "name": "Aerodynamic Heating",
    "description": "Study of aerodynamic heating and thermal protection systems.",
    "course": "RS102",
    "lessons": [
      {
        "_id": "L207",
        "name": "Thermal Protection Materials",
        "description": "Materials used for spacecraft thermal protection.",
        "module": "M203"
      },
      {
        "_id": "L208",
        "name": "Thermal Protection Systems",
        "description": "Designing and implementing thermal protection systems.",
        "module": "M203"
      },
      {
        "_id": "L209",
        "name": "Reentry Heating",
        "description": "Handling reentry heating during space missions.",
        "module": "M203"
      }
    ]
  },
  {
    "_id": "M301",
    "name": "Spacecraft Structural Design",
    "description": "Fundamentals of designing spacecraft structures and materials selection.",
    "course": "RS103",
    "lessons": [
      {
        "_id": "L301",
        "name": "Structural Components",
        "description": "Key components of spacecraft structural design.",
        "module": "M301"
      },
      {
        "_id": "L302",
        "name": "Materials Selection",
        "description": "Selecting materials for spacecraft structural components.",
        "module": "M301"
      },
      {
        "_id": "L303",
        "name": "Load Analysis",
        "description": "Analyzing and simulating structural loads in spacecraft design.",
        "module": "M301"
      }
    ]
  },
  {
    "_id": "M302",
    "name": "Orbital Mechanics",
    "description": "Understanding orbital dynamics and mission planning.",
    "course": "RS103",
    "lessons": [
      {
        "_id": "L304",
        "name": "Kepler's Laws",
        "description": "Laws governing planetary motion and orbits.",
        "module": "M302"
      },
      {
        "_id": "L305",
        "name": "Orbital Transfer Maneuvers",
        "description": "Performing orbital transfer maneuvers and station-keeping.",
        "module": "M302"
      },
      {
        "_id": "L306",
        "name": "Mission Planning",
        "description": "Planning space missions and trajectory optimization.",
        "module": "M302"
      }
    ]
  },
  {
    "_id": "M303",
    "name": "Spacecraft Systems Engineering",
    "description": "Overview of spacecraft systems and subsystems engineering.",
    "course": "RS103",
    "lessons": [
      {
        "_id": "L307",
        "name": "Systems Integration",
        "description": "Integration of subsystems in spacecraft design.",
        "module": "M303"
      },
      {
        "_id": "L308",
        "name": "Subsystems Integration",
        "description": "Integrating various subsystems in spacecraft design.",
        "module": "M303"
      },
      {
        "_id": "L309",
        "name": "Testing and Validation",
        "description": "Testing and validating spacecraft systems.",
        "module": "M303"
      }
    ]
  }
]